{"name": "Brian Kernighan", "abstract": "Brian Wilson Kernighan is a Canadian computer scientist who worked at Bell Labs alongside Unix creators Ken Thompson and Dennis Ritchie and contributed to the development of Unix. He is also coauthor of the AWK and AMPL programming languages.", "related_searches": ["Dennis Ritchie", "Rob Pike", "Ken Thompson", "Alfred Aho", "Peter J. Weinberger"], "wikipedia_url": "https://en.wikipedia.org/wiki/Brian_Kernighan", "image_file": "brian-kernighan.jpg", "related_books": ["The C Programming Language (1978)", "The Unix Programming Environment", "The Practice of Programming", "Software tools in Pascal", "The elements of programming style"]}