{"name": "David Heinemeier Hansson", "twitter_url": "https://twitter.com/dhh", "abstract": "David Heinemeier Hansson is a Danish programmer and the creator of the popular Ruby on Rails web development framework and the Instiki wiki. He is also a partner at the web-based software development firm 37signals.", "related_searches": ["why the lucky stiff", "Dave Thomas", "Yukihiro Matsumoto", "Sam Ruby", "Thomas Fuchs"], "wikipedia_url": "https://en.wikipedia.org/wiki/David_Heinemeier_Hansson", "image_file": "david-heinemeier-hansson.jpg"}