{"lang": "en", "friends_census": ["guidoguido", "janwaechter", "janwillemtulp", "joshuadehaseth", "moritz_stefaner", "thomasclever"], "statuses_count": 663, "description": "Co-Founder of @CLEVERFRANKE", "friends_count": 70, "url": "http://www.cleverfranke.com", "created_at": "2009-08-16T22:26:52", "followers_census": ["ashendruk", "guidoguido", "janwaechter", "janwillemtulp", "leogourven", "thomasclever"], "profile_image_url": "http://a0.twimg.com/profile_images/795096151/G_normal.jpg", "name": "gertfranke", "followers_count": 141, "protected": false, "screen_name": "gertfranke", "location": "Utrecht", "id": 66207916, "listed_count": 5}