{"lang": "en", "friends_census": ["alignedleft", "infosthetics", "janwillemtulp", "moritz_stefaner", "stefpos", "thewhyaxis", "visualisingdata"], "statuses_count": 90, "description": "MICA Creative Cog, Info Sponge, Mom, and Dabbler of All Stuff", "friends_count": 59, "url": null, "created_at": "2011-08-09T13:11:08", "followers_census": [], "profile_image_url": "http://a0.twimg.com/profile_images/2340645335/pahpfckm25y6kijew4tr_normal.jpeg", "name": "Heather Bradbury", "followers_count": 17, "protected": false, "screen_name": "gofish133", "location": "Baltimore", "id": 351580521, "listed_count": 4}