{"lang": "en", "friends_census": ["albertocairo", "arnicas", "ascheink", "christiansenjen", "datatelling", "driven_by_data", "dwtkns", "eagereyes", "eschow", "eyeseast", "flowingdata", "gabrielflorit", "infosthetics", "jakeporway", "janwillemtulp", "jcukier", "jeffclark", "jenniferdaniel", "katdowns", "larrybuch", "macdiva", "mattwynn", "mcgeoff", "moebio", "moritz_stefaner", "rachelbinx", "rsimmon", "shashashasha", "stefpos", "thewhyaxis", "visualecon", "visualisingdata", "visualized"], "statuses_count": 475, "description": "Graphics @ The New York Times. Alaskan. New Yorker. Now in D.C.", "friends_count": 367, "url": null, "created_at": "2009-03-18T16:05:12", "followers_census": ["_bmartinez_", "a_postma", "albertocairo", "alexlundry", "alignedleft", "amalax", "anhaeuser", "arnicas", "ashendruk", "billpalombi", "carlosalonso", "charlescrous", "cherdarchuk", "chiquiesteban", "christiansenjen", "cidfreitag", "cmdelaserna", "cybunk", "dalbers08", "danhillreports", "dataremixed", "datatelling", "davidjhodges", "dboptimizer", "dinocitraro", "driven_by_data", "drsvalbard", "dwtkns", "eagereyes", "eschow", "euanmackay", "exmathematician", "eyeseast", "francisgagnon", "fruys", "futuraprime", "gabrielflorit", "garveylatimes", "giorgialupi", "grahamvdr", "gregmore", "grjenkin", "hellomista", "hewart", "hlthanalysis", "illustrationkid", "infosthetics", "janwaechter", "janwillemtulp", "jcukier", "jeffclark", "jenniferdaniel", "jimmyc42", "joffley", "jonkeegan", "jorgelcortes", "jscarto", "jschwabish", "katdowns", "krees", "larrybuch", "lulupinney", "lydiaaguirre", "macdiva", "machikoyasuda", "mapchica", "mariame", "mattwynn", "mcgeoff", "mcristia", "mgroeninger", "miskaknapek", "mjmoore52", "moebio", "moritz_stefaner", "mpiccorossi", "mwtree", "nbrgraphs", "nunovargas", "officeofjane", "owenbriant", "p5k12", "parkgraeme", "pedrodmnunes", "perrymj", "rsimmon", "sciutoalex", "shashashasha", "shawnbot", "sheilabrobinson", "shevy", "smallmultiples", "stefpos", "storywithdata", "sylkegruhnwald", "thorlakur", "tifr1", "tomicrom", "tomp", "tvargs", "vanessashen", "visualecon", "visualisingdata", "visualized", "visualocean", "vizthinker", "vlandham", "walterra", "wiederkehr"], "profile_image_url": "http://a0.twimg.com/profile_images/927288329/HannahFairfieldWallander3_normal", "name": "Hannah Fairfield", "followers_count": 1574, "protected": false, "screen_name": "hfairfield", "location": "", "id": 25096930, "listed_count": 107}