{"lang": "en", "friends_census": ["albertocairo", "grahamvdr", "jburnmurdoch", "siyafrica", "visualisingdata"], "statuses_count": 6455, "description": "Visual storyteller. Loves history, royal families & typography. ", "friends_count": 1101, "url": "http://t.co/T0BmbihTKg", "created_at": "2009-03-19T08:10:38", "followers_census": ["grahamvdr", "siyafrica"], "profile_image_url": "http://a0.twimg.com/profile_images/3194050670/83dc4ca098f142480241734758e1c3e5_normal.jpeg", "name": "arlene_prinsloo", "followers_count": 266, "protected": false, "screen_name": "lenebelle", "location": "Cape Town", "id": 25258031, "listed_count": 6}