{"lang": "en", "friends_census": ["alignedleft", "ashendruk", "d3visualization", "driven_by_data", "dwtkns", "eyeseast", "gabrielflorit", "jakeporway", "katdowns", "lendegroot", "mattwynn", "myersjustinc", "nunovargas", "rdmurphy", "rsimmon", "vlandham"], "statuses_count": 10713, "description": "Data journalism & visualization @edmontonjournal. Jschool prof at MacEwan University. 2011 ONA MJ Bear Fellow. Today's Tom Sawyer, mean mean pride. ", "friends_count": 991, "url": "http://www.lucastimmons.com", "created_at": "2008-09-11T16:54:45", "followers_census": ["ashendruk", "camoesjo", "eyeseast", "lendegroot", "mattwynn", "myersjustinc"], "profile_image_url": "http://a0.twimg.com/profile_images/2735767700/aad968e3e3e3a4aadcf5374576764a7c_normal.png", "name": "Lucas Timmons", "followers_count": 1179, "protected": false, "screen_name": "lucastimmons", "location": "Edmonton, AB", "id": 16243488, "listed_count": 90}