{"lang": "en", "friends_census": ["euanmackay"], "statuses_count": 12637, "description": "I try to do things with poetry  at home and market research at Crowd DNA.\n\nI like stuff.", "friends_count": 1417, "url": "http://matriches76.wordpress.com/", "created_at": "2009-02-20T11:54:01", "followers_census": ["euanmackay"], "profile_image_url": "http://a0.twimg.com/profile_images/3033665759/0c45fb7343af0fdf3e5852f60d74bd9c_normal.jpeg", "name": "Mat Riches", "followers_count": 745, "protected": false, "screen_name": "matriches", "location": "London", "id": 21391194, "listed_count": 31}