{"dataid": "alberto-gilardino", "name": "Alberto Gilardino", "linked_from": ["giampaolo-pazzini", "marco-borriello", "manolo-gabbiadini", "luca-toni", "alessandro-diamanti", "adrian-mutu", "s-c3-a9bastien-frey", "stevan-joveti-c4-87"], "facebook_url": "https://www.facebook.com/pages/Alberto-Gilardino/9072911633", "level": 2, "related_searches": ["Giampaolo Pazzini", "Luca Toni", "Marco Borriello", "Alessandro Diamanti", "Adrian Mutu"], "to_merge": ["alberto gilardino", "Alberto Gilardino"], "image_file": "alberto-gilardino.jpg", "abstract": "Alberto Gilardino, Ufficiale OMRI is an Italian World Cup-winning footballer who plays as a striker for Serie A club Bologna and the Italian national team.", "wikipedia_url": "https://en.wikipedia.org/wiki/Alberto_Gilardino"}