{"dataid": "c3-89tienne-didot", "name": "\u00c9tienne Didot", "linked_from": ["cheikh-m-27bengue", "franck-tabanou", "ali-ahamada", "serge-aurier", "adrien-regattin"], "abstract": "\u00c9tienne Didot is a French football player currently playing for Toulouse in Ligue 1 after signing with them on 18 June 2008. He primarily plays as a centre midfielder.", "level": 4, "related_searches": ["Franck Tabanou", "Cheikh M'Bengue", "Serge Aurier", "Ali Ahamada", "Pantxi Sirieix"], "to_merge": ["\u00e9tienne didot", "\u00c9tienne Didot"], "image_file": "c3-89tienne-didot.jpg", "wikipedia_url": "https://en.wikipedia.org/wiki/%C3%89tienne_Didot"}