{"dataid": "c3-93scar-cardozo", "name": "\u00d3scar Cardozo", "level": 4, "abstract": "\u00d3scar Ren\u00e9 Cardozo Mar\u00edn is a Paraguayan professional footballer who plays for Benfica as a striker.", "linked_from": ["maximiliano-pereira"], "related_searches": ["Nicol\u00e1s Gait\u00e1n", "Luis\u00e3o", "Pablo Aimar", "Maximiliano Pereira", "Javier Saviola"], "to_merge": ["\u00f3scar cardozo", "\u00d3scar Cardozo"], "image_file": "c3-93scar-cardozo.jpg", "wikipedia_url": "https://en.wikipedia.org/wiki/%C3%93scar_Cardozo"}