{"dataid": "c5-81ukasz-fabia-c5-84ski", "name": "\u0141ukasz Fabia\u0144ski", "level": 4, "abstract": "\u0141ukasz Fabia\u0144ski is a Polish footballer who plays for English Premier League side Arsenal and the Polish national team as a goalkeeper. Fabia\u0144ski has represented his country on 21 occasions.", "linked_from": ["wojciech-szcz-c4-99sny", "manuel-almunia"], "related_searches": ["Vito Mannone", "Manuel Almunia", "Wojciech Szcz\u0119sny", "Johan Djourou", "S\u00e9bastien Squillaci"], "to_merge": ["\u0142ukasz fabia\u0144ski", "\u0141ukasz Fabia\u0144ski"], "image_file": "c5-81ukasz-fabia-c5-84ski.jpg", "wikipedia_url": "https://en.wikipedia.org/wiki/%C5%81ukasz_Fabia%C5%84ski"}