{"dataid": "eden-hazard", "name": "Eden Hazard", "linked_from": ["juan-mata", "oscar-footballer-born-1991", "victor-moses"], "twitter_url": "https://twitter.com/hazardeden10", "abstract": "Eden Hazard is a Belgian international footballer who plays for English club Chelsea in the Premier League and the Belgium national team. He primarily plays as an attacking midfielder and a winger.", "level": 0, "related_searches": ["Juan Mata", "Oscar dos Santos Emboaba Junior", "Fernando Torres", "Frank Lampard", "David Luiz"], "to_merge": ["eden hazard", "Eden Hazard"], "image_file": "eden-hazard.jpg", "facebook_url": "https://www.facebook.com/edenhazard", "wikipedia_url": "https://en.wikipedia.org/wiki/Eden_Hazard"}