{"dataid": "florent-malouda", "name": "Florent Malouda", "level": 2, "twitter_url": "https://twitter.com/realflorentm", "abstract": "Florent Johan Malouda is a French footballer currently employed by Chelsea. Once a prominent figure for the Club, Malouda is no longer a part of the First Team Squad, and now trains with the U21 Squad while seeing out the final year of his contract.", "linked_from": ["nicolas-anelka", "raul-meireles", "michael-essien", "salomon-kalou", "jos-c3-a9-bosingwa", "alou-diarra", "paulo-ferreira", "henrique-hil-c3-a1rio"], "related_searches": ["Salomon Kalou", "Nicolas Anelka", "Michael Essien", "Jos\u00e9 Bosingwa", "Branislav Ivanovi\u0107"], "to_merge": ["florent malouda", "Florent Malouda"], "image_file": "florent-malouda.jpg", "wikipedia_url": "https://en.wikipedia.org/wiki/Florent_Malouda"}