{"dataid": "ga-c3-abtan-charbonnier", "name": "Ga\u00ebtan Charbonnier", "level": 5, "twitter_url": "https://twitter.com/charbo10", "abstract": "Ga\u00ebtan Charbonnier is a French professional football player who currently plays as a striker for Ligue 1 club Montpellier HSC.", "linked_from": ["laurent-pionnier", "daniel-congr-c3-a9"], "related_searches": ["Daniel Congr\u00e9", "Anthony Mounier", "Emanuel Herrera", "R\u00e9my Cabella", "Laurent Pionnier"], "to_merge": ["ga\u00ebtan charbonnier", "Ga\u00ebtan Charbonnier"], "image_file": "ga-c3-abtan-charbonnier.jpg", "wikipedia_url": "https://en.wikipedia.org/wiki/Ga%C3%ABtan_Charbonnier"}