{"dataid": "gennaro-gattuso", "name": "Gennaro Gattuso", "linked_from": ["alessandro-nesta", "filippo-inzaghi", "clarence-seedorf", "gianluca-zambrotta", "massimo-ambrosini"], "facebook_url": "https://www.facebook.com/pages/Gennaro-Gattuso/28425470992", "level": 2, "related_searches": ["Filippo Inzaghi", "Clarence Seedorf", "Alessandro Nesta", "Gianluca Zambrotta", "Andrea Pirlo"], "to_merge": ["gennaro gattuso", "Gennaro Gattuso"], "image_file": "gennaro-gattuso.jpg", "abstract": "Gennaro Ivan \"Rino\" Gattuso, Ufficiale OMRI is an Italian professional footballer and a coach, who currently plays and manages Swiss Super League side FC Sion. He mainly plays as a defensive midfielder.", "wikipedia_url": "https://en.wikipedia.org/wiki/Gennaro_Gattuso"}