{"dataid": "jackson-mart-c3-adnez", "name": "Jackson Mart\u00ednez", "linked_from": ["james-rodr-c3-adguez-footballer", "james-rodr-c3-adguez-footballer"], "abstract": "Jackson Arley Mart\u00ednez Valencia is a Colombian footballer who plays as a striker for F.C. Porto of the Primeira Liga.", "level": 1, "related_searches": ["James Rodr\u00edguez", "Radamel Falcao Garc\u00eda", "Lucho Gonz\u00e1lez", "Eliaquim Mangala", "Silvestre Varela"], "to_merge": ["jackson mart\u00ednez", "Jackson Mart\u00ednez"], "image_file": "jackson-mart-c3-adnez.jpg", "wikipedia_url": "https://en.wikipedia.org/wiki/Jackson_Mart%C3%ADnez"}