{"dataid": "jakob-poulsen", "name": "Jakob Poulsen", "level": 3, "twitter_url": "https://twitter.com/Madsjpoulsen", "abstract": "Jakob Bendix Uhd Poulsen is a Danish professional football player in the midfielder position, playing for AS Monaco. Poulsen started his senior career with Esbjerg fB, before moving to Dutch side SC Heerenveen in 2006.", "linked_from": ["stephan-andersen", "niki-zimling", "lars-jacobsen", "thomas-kahlenberg"], "related_searches": ["Lars Jacobsen", "Stephan Andersen", "Simon Poulsen", "Dennis Rommedahl", "Niki Zimling"], "to_merge": ["jakob poulsen", "Jakob Poulsen"], "image_file": "jakob-poulsen.jpg", "wikipedia_url": "https://en.wikipedia.org/wiki/Jakob_Poulsen"}