{"dataid": "r-c3-a9mi-garde", "name": "R\u00e9mi Garde", "level": 4, "abstract": "R\u00e9mi Garde is a French football manager, and current coach of Lyon. Garde started his playing career at Lyon in 1982, helping the club achieve promotion to Ligue 1 in 1989.", "linked_from": ["lisandro-l-c3-b3pez", "baf-c3-a9timbi-gomis", "michel-bastos", "milan-bi-c5-a1evac"], "related_searches": ["Baf\u00e9timbi Gomis", "Lisandro L\u00f3pez", "Alexandre Lacazette", "Michel Bastos", "Maxime Gonalons"], "to_merge": ["r\u00e9mi garde", "R\u00e9mi Garde"], "image_file": "r-c3-a9mi-garde.jpg", "wikipedia_url": "https://en.wikipedia.org/wiki/R%C3%A9mi_Garde"}