{"dataid": "rog-c3-a9rio-ceni", "name": "Rog\u00e9rio Ceni", "level": 4, "abstract": "Rog\u00e9rio M\u00fccke Ceni is a Brazilian footballer who plays for S\u00e3o Paulo FC as a goalkeeper. Most of his professional career, which spanned more than two decades, was associated with S\u00e3o Paulo FC, with ...", "linked_from": ["lu-c3-ads-fabiano"], "related_searches": ["Lu\u00eds Fabiano", "Lucas Moura", "Paulo Henrique Ganso", "Jos\u00e9 Luis Chilavert", "Ney Franco"], "to_merge": ["rog\u00e9rio ceni", "Rog\u00e9rio Ceni"], "image_file": "rog-c3-a9rio-ceni.jpg", "wikipedia_url": "https://en.wikipedia.org/wiki/Rog%C3%A9rio_Ceni"}