{"dataid": "ron-robert-zieler", "name": "Ron-Robert Zieler", "level": 5, "abstract": "Ron-Robert Zieler is a German footballer who plays as a goalkeeper for Hannover 96 and the German national team.", "linked_from": ["jan-schlaudraff"], "related_searches": ["Jan Schlaudraff", "Karim Haggui", "Mohammed Abdellaoue", "Lars Stindl", "Marc-Andr\u00e9 ter Stegen"], "to_merge": ["ron-robert zieler", "Ron-Robert Zieler"], "image_file": "ron-robert-zieler.jpg", "wikipedia_url": "https://en.wikipedia.org/wiki/Ron-Robert_Zieler"}