{"dataid": "sergio-ag-c3-bcero", "name": "Sergio Ag\u00fcero", "linked_from": ["david-silva", "carlos-t-c3-a9vez", "mario-balotelli", "samir-nasri", "diego-forl-c3-a1n", "carlos-t-c3-a9vez", "edin-d-c5-beeko", "yaya-tour-c3-a9", "diego-forl-c3-a1n", "mario-balotelli", "diego-maradona"], "twitter_url": "https://twitter.com/aguerosergiokun", "abstract": "Sergio Leonel \"Kun\" Ag\u00fcero del Castillo is an Argentine footballer who plays as a striker for Premier League club Manchester City and the Argentine national team.", "level": 0, "related_searches": ["Carlos T\u00e9vez", "Edin D\u017eeko", "Samir Nasri", "Lionel Messi", "David Silva"], "to_merge": ["sergio aguero", "Sergio Ag\u00fcero"], "image_file": "sergio-ag-c3-bcero.jpg", "facebook_url": "https://www.facebook.com/sergioelkunaguero", "wikipedia_url": "https://en.wikipedia.org/wiki/Sergio_Ag%C3%BCero"}